connector_builder_mcp/__init__.py
connector_builder_mcp/_annotations.py
connector_builder_mcp/_checklist_utils.py
connector_builder_mcp/_manifest_history_utils.py
connector_builder_mcp/_manifest_scaffold_utils.py
connector_builder_mcp/_paths.py
connector_builder_mcp/_text_utils.py
connector_builder_mcp/_util.py
connector_builder_mcp/_validation_helpers.py
connector_builder_mcp/constants.py
connector_builder_mcp/server.py
connector_builder_mcp/_guidance/__init__.py
connector_builder_mcp/_guidance/connector_build_checklist.yml
connector_builder_mcp/_guidance/prompts.py
connector_builder_mcp/_guidance/topics.py
connector_builder_mcp/mcp/__init__.py
connector_builder_mcp/mcp/_mcp_utils.py
connector_builder_mcp/mcp/checklist.py
connector_builder_mcp/mcp/guidance.py
connector_builder_mcp/mcp/manifest_checks.py
connector_builder_mcp/mcp/manifest_edits.py
connector_builder_mcp/mcp/manifest_history.py
connector_builder_mcp/mcp/manifest_tests.py
connector_builder_mcp/mcp/prompts.py
connector_builder_mcp/mcp/secrets_config.py
connector_builder_mcp/mcp/server_info.py
connector_builder_mcp/resources/generated/connector-feature-index.csv
airbyte_connector_builder_mcp-0.6.0.dist-info/METADATA
airbyte_connector_builder_mcp-0.6.0.dist-info/WHEEL
airbyte_connector_builder_mcp-0.6.0.dist-info/entry_points.txt
airbyte_connector_builder_mcp-0.6.0.dist-info/RECORD
