Metadata-Version: 2.4
Name: airbyte-connector-builder-mcp
Version: 0.6.0
Summary: MCP server for Airbyte connector building operations with AI ownership focus
Author-email: Airbyte <contact@airbyte.io>
Requires-Python: >=3.11
Requires-Dist: airbyte-cdk<8.0,>=7.4.1
Requires-Dist: fastmcp<3.0,>=2.12.1
Requires-Dist: jsonschema<5.0,>=4.0.0
Requires-Dist: privatebin<1.0,>=0.3.0
Requires-Dist: pydantic<3.0,>=2.11.9
Requires-Dist: python-dotenv<2.0,>=1.1.1
Requires-Dist: pyyaml<7.0,>=6.0.0
Requires-Dist: requests<3.0,>=2.25.0
Requires-Dist: ruamel-yaml<0.18,>=0.17.21
